setup.py
bayes_on_redis/__init__.py
bayes_on_redis/bayes_on_redis.py
bayes_on_redis.egg-info/PKG-INFO
bayes_on_redis.egg-info/SOURCES.txt
bayes_on_redis.egg-info/dependency_links.txt
bayes_on_redis.egg-info/top_level.txt
test/test.py