Metadata-Version: 1.0
Name: bayes-on-redis
Version: 0.1.9
Summary: bayes_on_redis library provides bayesian classification on a given text similar to many SPAM/HAM filtering technique.
Home-page: https://github.com/didip/bayes_on_redis
Author: Didip Kerabat
Author-email: didipk@gmail.com
License: haven't decided
Keywords: bayesian filter redis
Platform: UNKNOWN
Classifier: Development Status :: 3 - Alpha
